cdiversity/__init__.py
cdiversity/cdiversity.py
cdiversity-1.0.1.dist-info/LICENSE
cdiversity-1.0.1.dist-info/METADATA
cdiversity-1.0.1.dist-info/WHEEL
cdiversity-1.0.1.dist-info/top_level.txt
cdiversity-1.0.1.dist-info/RECORD
