Metadata-Version: 2.1
Name: cdiversity
Version: 1.0.1
Summary: Quantifying B-Cell Clonal Diversity In Repertoire Data
Home-page: https://github.com/Aurelien-Pelissier/cdiversity
Author: Aurelien Pelissier
Author-email: aurelien.pelissier.38@gmail.com 
License: MIT
License-File: LICENSE
Requires-Dist: Levenshtein
Requires-Dist: sparse-dot-topn
